pyfastdoop/__init__.py
pyfastdoop/install.py
pyfastdoop/wrapper.py
pyfastdoop-1.0.1.dist-info/LICENSE
pyfastdoop-1.0.1.dist-info/METADATA
pyfastdoop-1.0.1.dist-info/WHEEL
pyfastdoop-1.0.1.dist-info/top_level.txt
pyfastdoop-1.0.1.dist-info/RECORD
