Metadata-Version: 2.1
Name: pyfastdoop
Version: 1.0.1
Summary: A Python wrapper for fastdoop library with Spark
Home-page: https://github.com/riccardoc95/pyfastdoop
Author: Riccardo Ceccaroni
Author-email: riccardo.ceccaroni@uniroma1.it
Classifier: Programming Language :: Python :: 3
Classifier: License :: OSI Approved :: Apache Software License
Requires-Python: >=3.6
License-File: LICENSE
Requires-Dist: pyspark<4.0.0,>=3.0.0
